lektor_hal.py
lektor_hal-0.1.2.dist-info/METADATA
lektor_hal-0.1.2.dist-info/WHEEL
lektor_hal-0.1.2.dist-info/entry_points.txt
lektor_hal-0.1.2.dist-info/top_level.txt
lektor_hal-0.1.2.dist-info/RECORD
