Metadata-Version: 2.1
Name: lektor-hal
Version: 0.1.2
Summary: Fetches publications from HAL
Home-page: https://git.sr.ht/~nicoco/lektor-hal
Author: Nicolas Cedilnik
Author-email: nicoco@nicoco.fr
License: MIT
Keywords: Lektor plugin static-site blog
Platform: UNKNOWN
Classifier: Framework :: Lektor
Classifier: Environment :: Web Environment
Classifier: Environment :: Plugins
Classifier: License :: OSI Approved :: MIT License
Requires: requests
Requires: lektor
